MANIFEST.in
README.md
setup.py
mime/__init__.py
mime/mime_types.py
mime/type.py
mime.egg-info/PKG-INFO
mime.egg-info/SOURCES.txt
mime.egg-info/dependency_links.txt
mime.egg-info/top_level.txt
mime/types/application
mime/types/application.mac
mime/types/application.nonstandard
mime/types/application.obsolete
mime/types/audio
mime/types/audio.nonstandard
mime/types/audio.obsolete
mime/types/image
mime/types/image.nonstandard
mime/types/image.obsolete
mime/types/message
mime/types/message.obsolete
mime/types/model
mime/types/multipart
mime/types/multipart.nonstandard
mime/types/multipart.obsolete
mime/types/other.nonstandard
mime/types/text
mime/types/text.nonstandard
mime/types/text.obsolete
mime/types/text.vms
mime/types/video
mime/types/video.nonstandard
mime/types/video.obsolete
tests/__init__.py
tests/framework.py
tests/run.py
tests/test_type.py
tests/test_types.py