Metadata-Version: 1.1
Name: mime
Version: 0.0.3
Summary: MIME Types
Home-page: https://github.com/liluo/mime
Author: liluo
Author-email: i@liluo.org
License: MIT License
Keywords: mime types
Platform: POSIX
Classifier: Programming Language :: Python
Classifier: Operating System :: POSIX
